pasta/__init__.py
pasta/augment/__init__.py
pasta/augment/errors.py
pasta/augment/import_utils.py
pasta/augment/import_utils_test.py
pasta/augment/inline.py
pasta/augment/inline_test.py
pasta/augment/rename.py
pasta/augment/rename_test.py
pasta/base/__init__.py
pasta/base/annotate.py
pasta/base/annotate_test.py
pasta/base/ast_constants.py
pasta/base/ast_utils.py
pasta/base/ast_utils_test.py
pasta/base/codegen.py
pasta/base/codegen_test.py
pasta/base/formatting.py
pasta/base/fstring_utils.py
pasta/base/scope.py
pasta/base/scope_test.py
pasta/base/test_utils.py
pasta/base/test_utils_test.py
pasta/base/token_generator.py
google_pasta-0.1.8.dist-info/LICENSE
google_pasta-0.1.8.dist-info/METADATA
google_pasta-0.1.8.dist-info/WHEEL
google_pasta-0.1.8.dist-info/top_level.txt
google_pasta-0.1.8.dist-info/RECORD
