Metadata-Version: 1.1
Name: google-pasta
Version: 0.1.8
Summary: pasta is an AST-based Python refactoring library
Home-page: UNKNOWN
Author: Nick Smith
Author-email: smithnick@google.com
License: Apache 2.0
Keywords: python refactoring ast
Platform: UNKNOWN
Classifier: Development Status :: 2 - Pre-Alpha
Classifier: License :: OSI Approved :: Apache Software License
Classifier: Programming Language :: Python
Classifier: Programming Language :: Python :: 2.7
Classifier: Programming Language :: Python :: 3
Classifier: Programming Language :: Python :: 3.4
Classifier: Programming Language :: Python :: 3.5
Classifier: Programming Language :: Python :: 3.6
